photoncube-0.3.16.dist-info/METADATA
photoncube-0.3.16.dist-info/WHEEL
photoncube-0.3.16.dist-info/entry_points.txt
photoncube-0.3.16.dist-info/licenses/LICENSE
photoncube/__init__.py
photoncube/photoncube.cpython-312-aarch64-linux-gnu.so
photoncube-0.3.16.dist-info/RECORD
